areq/__init__.py
areq/api.py
areq/exceptions.py
areq/models.py
areq-0.0.5.dist-info/licenses/LICENSE
areq-0.0.5.dist-info/METADATA
areq-0.0.5.dist-info/WHEEL
areq-0.0.5.dist-info/top_level.txt
areq-0.0.5.dist-info/RECORD
