Metadata-Version: 2.4
Name: areq
Version: 0.0.5
Summary: Asynchronous requests package
Author-email: Ganesh Palanikumar <ganeshpkumar93@gmail.com>
License-Expression: MIT
Project-URL: Homepage, https://github.com/ganesh-palanikumar/areq
Project-URL: Issues, https://github.com/ganesh-palanikumar/areq/issues
Classifier: Programming Language :: Python :: 3
Classifier: Operating System :: OS Independent
Requires-Python: >=3.9
License-File: LICENSE
Dynamic: license-file
